{
  "generator-jhipster": {
    "applicationType": "gateway",
    "authenticationType": "oauth2",
    "baseName": "jhipsterCognitoGateway",
    "blueprints": [],
    "buildTool": "maven",
    "cacheProvider": "ehcache",
    "clientFramework": "angularX",
    "clientPackageManager": "npm",
    "clientTheme": "none",
    "clientThemeVariant": "",
    "creationTimestamp": 1643782094955,
    "databaseType": "sql",
    "devDatabaseType": "h2Disk",
    "devServerPort": 4200,
    "dtoSuffix": "DTO",
    "enableGradleEnterprise": false,
    "enableHibernateCache": true,
    "enableSwaggerCodegen": false,
    "enableTranslation": true,
    "entitySuffix": "",
    "gitCompany": "",
    "jhiPrefix": "jhi",
    "jhipsterVersion": "7.6.0",
    "jwtSecretKey": "ODU3YTU2NDNlMjQwZjdjYTVkMTkzMzM5YTk1NDY3NTJkZTRhNTYwZTZiNDQ5NmI5YmVlZjQ4NGIwOTY3MWY1ZTM1ZWExY2JmMWE4NzRjODlmYTYyOTM5MzJiNTU3NDZjODQ2YzQ0NDBiZTg4MDM0MWVkMDkzMjYxNjcwNmYxYzY=",
    "languages": ["en"],
    "messageBroker": false,
    "nativeLanguage": "en",
    "otherModules": [],
    "packageFolder": "com/mycompany/myapp",
    "packageName": "com.mycompany.myapp",
    "pages": [],
    "prodDatabaseType": "mysql",
    "reactive": true,
    "searchEngine": false,
    "serverPort": 8080,
    "serviceDiscoveryType": "eureka",
    "skipCheckLengthOfIdentifier": false,
    "skipFakeData": false,
    "skipUserManagement": true,
    "testFrameworks": [],
    "useSass": true,
    "websocket": false,
    "withAdminUi": true
  },
  "git-provider": "GitHub",
  "git-company": "djanakiram",
  "repository-name": "jhipster-cognito-gateway"
}
